pnmac_aws_common/__init__.py
pnmac_aws_common/secretsmanager.py
pnmac_aws_common/sqs.py
pnmac_aws_common-0.0.7.dist-info/METADATA
pnmac_aws_common-0.0.7.dist-info/RECORD
pnmac_aws_common-0.0.7.dist-info/WHEEL
pnmac_aws_common-0.0.7.dist-info/top_level.txt
