Metadata-Version: 2.1
Name: pnmac-aws-common
Version: 0.0.7
Summary: A set of utilities to use with AWS
Home-page: https://gitlab.pnmac.com/martech/pnmac-aws-secrets
Author: Example Author
Author-email: none@example.com
License: UNKNOWN
Platform: UNKNOWN
Classifier: Programming Language :: Python :: 3
Classifier: License :: OSI Approved :: MIT License
Classifier: Operating System :: OS Independent
